openai_stream/__init__.py
openai_stream-0.0.1.dist-info/METADATA
openai_stream-0.0.1.dist-info/WHEEL
openai_stream-0.0.1.dist-info/RECORD
